{
  "name": "arkival",
  "version": "1.1.262",
  "description": "AI Agent Workflow Orchestration System for seamless knowledge transfer between AI agents and human developers",
  "type": "module",
  "scripts": {
    "setup": "python3 setup_workflow_system.py",
    "verify": "python3 -c \"import sys; print('Python version:', sys.version); print('Setup ready!')\"",
    "test": "python3 test_enhanced_features.py",
    "validate": "python3 validate_deployment.py"
  },
  "keywords": ["ai-agent", "workflow-orchestration", "knowledge-transfer", "cross-platform", "replit", "vscode", "cursor", "arkival"],
  "author": "Spitfire Products",
  "license": "SEE LICENSE IN LICENSE",
  "engines": {
    "python": ">=3.7"
  },
  "repository": {
    "type": "git",
    "url": "https://github.com/spitfire-products/arkival.git"
  },
  "homepage": "https://github.com/spitfire-products/arkival#readme",
  "bugs": {
    "url": "https://github.com/spitfire-products/arkival/issues"
  }
}
