{
  "_generator": "Generated by codebase_summary/agent_workflow_orchestrator.py - Agent session state management",
  "last_session": {
    "timestamp": "2025-06-18T08:14:06.178833Z",
    "summary": "Completed comprehensive documentation update post-refactor. Fixed version tracking decoupling, merged data from subdirectory testing, updated all documentation to reflect dual deployment modes, enhanced auto-generated docs, and resolved archive path issues. System now fully documented with both manual and auto-generated files reflecting the universal path resolution and subdirectory deployment capabilities.",
    "type": "completed",
    "handoff_ready": true
  },
  "project_version": "1.1.10",
  "next_agent_context": {
    "priority_items": [],
    "technical_state": {
      "application_running": true,
      "last_build_status": "success",
      "critical_errors": [],
      "performance_status": "normal"
    },
    "known_issues": []
  }
}